barcalc/__init__.py
barcalc/tools.py
barcalc-0.0.1.dist-info/METADATA
barcalc-0.0.1.dist-info/WHEEL
barcalc-0.0.1.dist-info/licenses/LICENSE.txt
barcalc-0.0.1.dist-info/RECORD
