Metadata-Version: 2.1
Name: barcalc
Version: 0.0.1
Summary: Bar data calculation routines
Author-email: Furechan <furechan@xsmail.com>
License: MIT
License-File: LICENSE.txt
Keywords: data,finance
Classifier: Programming Language :: Python :: 3
Requires-Python: >=3.9
Requires-Dist: pandas
Requires-Dist: scikit-learn
